{
  "project_info": {
    "project_number": "224124334619",
    "project_id": "lms-app-5257f",
    "storage_bucket": "lms-app-5257f.appspot.com"
  },
  "client": [
    {
      "client_info": {
        "mobilesdk_app_id": "1:224124334619:android:6e6bc3e6ac59c5cac37ebe",
        "android_client_info": {
          "package_name": "com.example.lms"
        }
      },
      "oauth_client": [
        {
          "client_id": "224124334619-ks02k2pot0u3pdjdrd3q01bjuub6fv7q.apps.googleusercontent.com",
          "client_type": 3
        }
      ],
      "api_key": [
        {
          "current_key": "AIzaSyDuyLJUee9xnsfuaJmB6-AQ02_xZEzYbc0"
        }
      ],
      "services": {
        "appinvite_service": {
          "other_platform_oauth_client": [
            {
              "client_id": "224124334619-ks02k2pot0u3pdjdrd3q01bjuub6fv7q.apps.googleusercontent.com",
              "client_type": 3
            },
            {
              "client_id": "224124334619-s73jjig7hh3hjsg5dveq58nvfcarg41p.apps.googleusercontent.com",
              "client_type": 2,
              "ios_info": {
                "bundle_id": "com.example.lms"
              }
            }
          ]
        }
      }
    },
    {
      "client_info": {
        "mobilesdk_app_id": "1:224124334619:android:f5f83644cf045ac8c37ebe",
        "android_client_info": {
          "package_name": "com.example.soil_test"
        }
      },
      "oauth_client": [
        {
          "client_id": "224124334619-ks02k2pot0u3pdjdrd3q01bjuub6fv7q.apps.googleusercontent.com",
          "client_type": 3
        }
      ],
      "api_key": [
        {
          "current_key": "AIzaSyDuyLJUee9xnsfuaJmB6-AQ02_xZEzYbc0"
        }
      ],
      "services": {
        "appinvite_service": {
          "other_platform_oauth_client": [
            {
              "client_id": "224124334619-ks02k2pot0u3pdjdrd3q01bjuub6fv7q.apps.googleusercontent.com",
              "client_type": 3
            },
            {
              "client_id": "224124334619-s73jjig7hh3hjsg5dveq58nvfcarg41p.apps.googleusercontent.com",
              "client_type": 2,
              "ios_info": {
                "bundle_id": "com.example.lms"
              }
            }
          ]
        }
      }
    }
  ],
  "configuration_version": "1"
}